Metadata-Version: 2.1
Name: odoo12-addon-report-py3o-fusion-server
Version: 12.0.1.0.2
Summary: Let the fusion server handle format conversion.
Home-page: https://github.com/OCA/reporting-engine
Author: XCG Consulting,ACSONE SA/NV,Odoo Community Association (OCA)
Author-email: support@odoo-community.org
License: AGPL-3
Platform: UNKNOWN
Classifier: Programming Language :: Python
Classifier: Framework :: Odoo
Classifier: Framework :: Odoo :: 12.0
Classifier: License :: OSI Approved :: GNU Affero General Public License v3
Requires-Python: >=3.5
Requires-Dist: odoo12-addon-report-py3o
Requires-Dist: odoo (<12.1dev,>=12.0a)
Requires-Dist: py3o.formats
Requires-Dist: py3o.template
